src/__init__.py
src/scrapec.py
scrapec-20.6.5.dist-info/LICENSE
scrapec-20.6.5.dist-info/METADATA
scrapec-20.6.5.dist-info/WHEEL
scrapec-20.6.5.dist-info/entry_points.txt
scrapec-20.6.5.dist-info/top_level.txt
scrapec-20.6.5.dist-info/RECORD
